admin_kit/__init__.py
admin_kit/ajax.py
admin_kit/apps.py
admin_kit/fields.py
admin_kit/models.py
admin_kit/sites.py
admin_kit/widgets.py
admin_kit/static/admin_kit/css/base.scss
admin_kit/static/admin_kit/css/select.css
admin_kit/static/admin_kit/css/select.scss
admin_kit/static/admin_kit/css/select2.min.css
admin_kit/static/admin_kit/js/base.js
admin_kit/static/admin_kit/js/jquery-3.6.0.min.js
admin_kit/static/admin_kit/js/select2.min.js
admin_kit/templates/admin/change_form.html
admin_kit/templates/admin_kit/config.js
admin_kit/templates/admin_kit/ping.html
admin_kit/templates/admin_kit/widgets/select.html
admin_kit/templates/admin_kit/widgets/select_option.html
tests/__init__.py
tests/settings.py
tests/urls.py
tests/test_ajax/__init__.py
tests/test_ajax/ajax.py
tests/test_ajax/tests.py
tests/test_ajax_duplicate/__init__.py
tests/test_ajax_duplicate/admin.py
tests/test_ajax_duplicate/ajax.py
tests/test_ajax_duplicate/models.py
tests/test_ajax_duplicate/tests.py
tests/test_duplicate/__init__.py
tests/test_duplicate/admin.py
tests/test_duplicate/models.py
tests/test_duplicate/tests.py
tests/test_model/__init__.py
tests/test_model/models.py
tests/test_model/tests.py
tests/test_ping/__init__.py
tests/test_ping/models.py
tests/test_ping/tests.py
django_admin_kit-0.0.20.dist-info/LICENSE
django_admin_kit-0.0.20.dist-info/METADATA
django_admin_kit-0.0.20.dist-info/WHEEL
django_admin_kit-0.0.20.dist-info/top_level.txt
django_admin_kit-0.0.20.dist-info/RECORD
