Metadata-Version: 2.1
Name: django-admin-kit
Version: 0.0.20
Summary: Django Admin Kit provides additional features to Django Admin
Home-page: https://github.com/RohanPoojary/django-admin-kit
Author: Rohan Poojary
Author-email: rohanrp23@gmail.com
License: MIT
Platform: any
Classifier: Development Status :: 5 - Production/Stable
Classifier: Environment :: Web Environment
Classifier: Intended Audience :: Developers
Classifier: Operating System :: OS Independent
Classifier: Programming Language :: Python :: 3.5
Classifier: Programming Language :: Python :: 3.6
Classifier: Framework :: Django :: 1.11
Requires-Python: >=3
License-File: LICENSE
